{
  "db_name": "SQLite",
  "query": "\n        SELECT id, name, email,\n            created_at AS \"created_at: DateTime<Utc>\",\n            updated_at AS \"updated_at: DateTime<Utc>\"\n        FROM users",
  "describe": {
    "columns": [
      {
        "name": "id",
        "ordinal": 0,
        "type_info": "Integer",
        "origin": {
          "Table": {
            "table": "users",
            "name": "id"
          }
        }
      },
      {
        "name": "name",
        "ordinal": 1,
        "type_info": "Text",
        "origin": {
          "Table": {
            "table": "users",
            "name": "name"
          }
        }
      },
      {
        "name": "email",
        "ordinal": 2,
        "type_info": "Text",
        "origin": {
          "Table": {
            "table": "users",
            "name": "email"
          }
        }
      },
      {
        "name": "created_at: DateTime<Utc>",
        "ordinal": 3,
        "type_info": "Datetime",
        "origin": {
          "Table": {
            "table": "users",
            "name": "created_at"
          }
        }
      },
      {
        "name": "updated_at: DateTime<Utc>",
        "ordinal": 4,
        "type_info": "Datetime",
        "origin": {
          "Table": {
            "table": "users",
            "name": "updated_at"
          }
        }
      }
    ],
    "parameters": {
      "Right": 0
    },
    "nullable": [
      false,
      false,
      false,
      false,
      false
    ]
  },
  "hash": "8792b1c20399c4067ff6e669b8680c0db8c01b054b4b0f6cc30d1ec5fbf0560c"
}
